mdf/__init__.py
mdf/cli.py
mdf/parser.py
mdf/templates.py
mdf/writer.py
markdown_to_files-1.0.0.dist-info/METADATA
markdown_to_files-1.0.0.dist-info/WHEEL
markdown_to_files-1.0.0.dist-info/entry_points.txt
markdown_to_files-1.0.0.dist-info/top_level.txt
markdown_to_files-1.0.0.dist-info/RECORD
