Metadata-Version: 2.4
Name: markdown-to-files
Version: 1.0.0
Summary: Generate project structures from markdown files
Home-page: https://github.com/JahanzebAhmed12/project_maker
Author: Jahanzeb Ahmed
Author-email: Jahanzeb Ahmed <jahanzebahmed12pk@gmail.com>
License: MIT
Project-URL: Homepage, https://github.com/JahanzebAhmed12/project_maker
Project-URL: Bug Tracker, https://github.com/JahanzebAhmed12/project_maker/issues
Project-URL: Documentation, https://github.com/JahanzebAhmed12/project_maker#readme
Classifier: Development Status :: 4 - Beta
Classifier: Intended Audience :: Developers
Classifier: Topic :: Software Development :: Build Tools
Classifier: License :: OSI Approved :: MIT License
Classifier: Programming Language :: Python :: 3
Classifier: Programming Language :: Python :: 3.8
Classifier: Programming Language :: Python :: 3.9
Classifier: Programming Language :: Python :: 3.10
Classifier: Programming Language :: Python :: 3.11
Requires-Python: >=3.8
Requires-Dist: click>=8.0.0
Requires-Dist: pyyaml>=6.0
Requires-Dist: colorama>=0.4.0
Requires-Dist: jinja2>=3.0.0
Dynamic: author
Dynamic: home-page
Dynamic: requires-python
